MANIFEST.in
README.rst
setup.cfg
setup.py
doc/.gitignore
doc/Makefile
doc/buffer.rst
doc/conf.py
doc/examples.rst
doc/graph.rst
doc/index.rst
doc/installation.rst
doc/make.bat
doc/out
doc/pcollections.rst
doc/reference.rst
doc/roadmap.rst
doc/storage.rst
doc/_build/html/.buildinfo
doc/_build/html/buffer.html
doc/_build/html/examples.html
doc/_build/html/genindex.html
doc/_build/html/gettingStarted.html
doc/_build/html/graph.html
doc/_build/html/index.html
doc/_build/html/installation.html
doc/_build/html/objects.inv
doc/_build/html/pcollections.html
doc/_build/html/py-modindex.html
doc/_build/html/reference.html
doc/_build/html/roadmap.html
doc/_build/html/search.html
doc/_build/html/searchindex.js
doc/_build/html/storage.html
doc/_build/html/_modules/index.html
doc/_build/html/_sources/buffer.txt
doc/_build/html/_sources/examples.txt
doc/_build/html/_sources/gettingStarted.txt
doc/_build/html/_sources/graph.txt
doc/_build/html/_sources/index.txt
doc/_build/html/_sources/installation.txt
doc/_build/html/_sources/pcollections.txt
doc/_build/html/_sources/reference.txt
doc/_build/html/_sources/roadmap.txt
doc/_build/html/_sources/storage.txt
doc/_build/html/_sources/contributing/contributorsGuide.txt
doc/_build/html/_sources/contributing/lessonsLearnt.txt
doc/_build/html/_static/ajax-loader.gif
doc/_build/html/_static/basic.css
doc/_build/html/_static/comment-bright.png
doc/_build/html/_static/comment-close.png
doc/_build/html/_static/comment.png
doc/_build/html/_static/default.css
doc/_build/html/_static/doctools.js
doc/_build/html/_static/down-pressed.png
doc/_build/html/_static/down.png
doc/_build/html/_static/file.png
doc/_build/html/_static/jquery.js
doc/_build/html/_static/minus.png
doc/_build/html/_static/plus.png
doc/_build/html/_static/pygments.css
doc/_build/html/_static/searchtools.js
doc/_build/html/_static/sidebar.js
doc/_build/html/_static/underscore.js
doc/_build/html/_static/up-pressed.png
doc/_build/html/_static/up.png
ptypes.egg-info/PKG-INFO
ptypes.egg-info/SOURCES.txt
ptypes.egg-info/dependency_links.txt
ptypes.egg-info/pbr.json
ptypes.egg-info/top_level.txt