Metadata-Version: 1.1
Name: ptypes
Version: 0.5.0
Summary: Persistent types: storing objects in memory-mapped files without serializing
Home-page: https://github.com/AmadeusITGroup/ptypes
Author: Dénes Vadász
Author-email: dvadasz@amadeus.com
License: Apache
Download-URL: https://pypi.python.org/pypi/ptypes
Keywords: persistency mmap
Platform: UNKNOWN
Classifier: Development Status :: 3 - Alpha
Classifier: Intended Audience :: Developers
Classifier: Topic :: Software Development :: Libraries
Classifier: Topic :: Software Development :: Libraries :: Python Modules
Classifier: Topic :: Scientific/Engineering
Classifier: Topic :: Database
Classifier: License :: OSI Approved :: Apache Software License
Classifier: Operating System :: POSIX
Classifier: Programming Language :: CythonProgramming Language :: CProgramming Language :: Python :: 2
Classifier: Programming Language :: Python :: 2.7
Classifier: Programming Language :: Python :: Implementation :: CPython
